bornhack_sl400/bornhack_sl400.py
bornhack_sl400-0.0.2.dist-info/METADATA
bornhack_sl400-0.0.2.dist-info/WHEEL
bornhack_sl400-0.0.2.dist-info/entry_points.txt
bornhack_sl400-0.0.2.dist-info/licenses/LICENSE
bornhack_sl400-0.0.2.dist-info/RECORD
