Metadata-Version: 2.3
Name: bornhack_sl400
Version: 0.0.2
Summary: Convert the BornHack phonebook to vCard for the Gigaset SL400
Project-URL: Homepage, https://codeberg.org/eloy/bornhack_sl400/
Project-URL: Issues, https://codeberg.org/eloy/bornhack_sl400/issues
Author-email: Eloy <mail@eloydegen.com>
License-File: LICENSE
Requires-Python: >=3.7
Requires-Dist: quicksync4linux
Requires-Dist: requests
Requires-Dist: vobject
